analyze_stocks_india/Mean_Reverser_Strategy.py
analyze_stocks_india/__init__.py
analyze_stocks_india/create_data_dir.py
analyze_stocks_india/create_plots.py
analyze_stocks_india/download_historic_data.py
analyze_stocks_india/get_stock_moment_from_optionChain.py
analyze_stocks_india/holidays.py
analyze_stocks_india/news_sentiment_analysis_Indian_Stocks.py
analyze_stocks_india/nse_archives.py
analyze_stocks_india/nse_history.py
analyze_stocks_india/nse_live.py
analyze_stocks_india/nse_symbols.py
analyze_stocks_india/supporting_functions.py
analyze_stocks_india_sample_scripts/sample_script_download_and_extract_data.py
analyze_stocks_india_sample_scripts/sample_script_get_stocks_from_optionChain.py
analyze_stocks_india_sample_scripts/sample_script_get_stocks_mean_reverser_strategy.py
analyze_stocks_india_sample_scripts/sample_script_get_symbols.py
analyze_stocks_india_sample_scripts/sample_script_google_news_sentiment_analysis.py
analyze_stocks_india_sample_scripts/sample_script_visualize_data.py
analyze_stocks_india-1.0.2.dist-info/LICENSE
analyze_stocks_india-1.0.2.dist-info/METADATA
analyze_stocks_india-1.0.2.dist-info/WHEEL
analyze_stocks_india-1.0.2.dist-info/top_level.txt
analyze_stocks_india-1.0.2.dist-info/RECORD
