Metadata-Version: 2.1
Name: analyze_stocks_india
Version: 1.0.2
Summary: A python package to download historic stock prices from NSE website and process them to find best stock to purchase
Author: Prasanna Raut
Author-email: Prasanna Raut <prasannaraut36@gmail.com>
Project-URL: Homepage, https://github.com/prasannaraut/analyze_stocks_india
Project-URL: Issues, https://github.com/prasannaraut/analyze_stocks_india/blob/main/issues
Classifier: Programming Language :: Python :: 3
Classifier: License :: OSI Approved :: MIT License
Classifier: Programming Language :: Python
Requires-Python: >=3.6
License-File: LICENSE
Requires-Dist: numpy >=1.19.5
Requires-Dist: pandas >=1.1.5
Requires-Dist: nltk >=3.6.7
Requires-Dist: plotly >=5.18.0
Requires-Dist: requests >=2.27.1
Requires-Dist: bs4
Requires-Dist: tenacity >=8.2.2
